byted_overpass_capcut_cloud_edit_matrix/__init__.py
byted_overpass_capcut_cloud_edit_matrix-0.0.1.dist-info/METADATA
byted_overpass_capcut_cloud_edit_matrix-0.0.1.dist-info/WHEEL
byted_overpass_capcut_cloud_edit_matrix-0.0.1.dist-info/top_level.txt
byted_overpass_capcut_cloud_edit_matrix-0.0.1.dist-info/RECORD
